pypassmanager/__init__.py
pypassmanager/password_manager.py
pypassmanager/password_safe.py
pypassmanager/text_wrappers.py
pypassmanager-2.0.0.dist-info/LICENSE
pypassmanager-2.0.0.dist-info/METADATA
pypassmanager-2.0.0.dist-info/WHEEL
pypassmanager-2.0.0.dist-info/entry_points.txt
pypassmanager-2.0.0.dist-info/top_level.txt
pypassmanager-2.0.0.dist-info/RECORD
