Metadata-Version: 2.1
Name: pypassmanager
Version: 2.0.0
Summary: Python Password Manager
Home-page: https://github.com/11ajith/pypassman
Author: Ajith S
Author-email: ajiths1311@gmail.com
License: MIT
Platform: UNKNOWN
Classifier: Programming Language :: Python :: 3
Classifier: License :: OSI Approved :: MIT License
Classifier: Operating System :: OS Independent
Requires-Python: >=3.6
Requires-Dist: bcrypt
Requires-Dist: pyperclip
Requires-Dist: cryptography
